xmod/__init__.py
xmod/py.typed
xmod-1.8.0.dist-info/LICENSE
xmod-1.8.0.dist-info/METADATA
xmod-1.8.0.dist-info/WHEEL
xmod-1.8.0.dist-info/RECORD
